Workbook
Name Slicer_Months__date: #N/A

Sheet Web Series Ratings
A1: S.No | B1: date | C1: Industry | D1: Web Series Name | E1: Genre | F1: Rating (1-5) | G1: Review | H1: Platform | I1: Viewers (Millions) | J1: Price Per Viewer (₹) | K1: Total Sales (₹ Crore) | L1: Profit (₹ Crore)
A2: 1 | B2: 45761 | C2: Tollywood | D2: The Family Man | E2: Action | F2: 4 | G2: Good | H2: Hotstar | I2: 49.1 | J2: 15 | K2: =ROUND(I2*J2/100,2) -> 7.37 | L2: =ROUND(K2*0.4,2) -> 2.95
A3: 2 | B3: 45755 | C3: Chinese | D3: The Rise of Phoenixes | E3: Action | F3: 5 | G3: Must Watch | H3: Netflix | I3: 80.4 | J3: 14 | K3: =ROUND(I3*J3/100,2) -> 11.26 | L3: =ROUND(K3*0.4,2) -> 4.5
A4: 3 | B4: 45709 | C4: Bollywood | D4: Tandav | E4: Comedy | F4: 2 | G4: Poor | H4: SonyLIV | I4: 3 | J4: 20 | K4: =ROUND(I4*J4/100,2) -> 0.6 | L4: =ROUND(K4*0.4,2) -> 0.24
A5: 4 | B5: 45811 | C5: Tollywood | D5: Farhana | E5: Horror | F5: 5 | G5: Must Watch | H5: Amazon Prime | I5: 78.2 | J5: 11 | K5: =ROUND(I5*J5/100,2) -> 8.6 | L5: =ROUND(K5*0.4,2) -> 3.44
A6: 5 | B6: 45703 | C6: Bollywood | D6: Grahan | E6: Crime | F6: 4 | G6: Good | H6: Netflix | I6: 48.8 | J6: 16 | K6: =ROUND(I6*J6/100,2) -> 7.81 | L6: =ROUND(K6*0.4,2) -> 3.12
A7: 6 | B7: 45716 | C7: Bollywood | D7: Kaala Paani | E7: Comedy | F7: 5 | G7: Must Watch | H7: Hotstar | I7: 82.3 | J7: 16 | K7: =ROUND(I7*J7/100,2) -> 13.17 | L7: =ROUND(K7*0.4,2) -> 5.27
A8: 7 | B8: 45721 | C8: Hollywood | D8: Downton Abbey | E8: Fantasy | F8: 3 | G8: Average | H8: SonyLIV | I8: 19.5 | J8: 20 | K8: =ROUND(I8*J8/100,2) -> 3.9 | L8: =ROUND(K8*0.4,2) -> 1.56
A9: 8 | B9: 45692 | C9: Hollywood | D9: The Office | E9: Thriller | F9: 4 | G9: Good | H9: Netflix | I9: 32.2 | J9: 21 | K9: =ROUND(I9*J9/100,2) -> 6.76 | L9: =ROUND(K9*0.4,2) -> 2.7
A10: 9 | B10: 45680 | C10: Bollywood | D10: Feels Like Ishq | E10: Crime | F10: 4 | G10: Good | H10: Hotstar | I10: 38.6 | J10: 19 | K10: =ROUND(I10*J10/100,2) -> 7.33 | L10: =ROUND(K10*0.4,2) -> 2.93
A11: 10 | B11: 45722 | C11: Hollywood | D11: Seinfeld | E11: Action | F11: 4 | G11: Good | H11: Amazon Prime | I11: 46.4 | J11: 22 | K11: =ROUND(I11*J11/100,2) -> 10.21 | L11: =ROUND(K11*0.4,2) -> 4.08
A12: 11 | B12: 45756 | C12: Chinese | D12: Arsenal Military Academy | E12: Comedy | F12: 5 | G12: Must Watch | H12: Hotstar | I12: 49.8 | J12: 16 | K12: =ROUND(I12*J12/100,2) -> 7.97 | L12: =ROUND(K12*0.4,2) -> 3.19
A13: 12 | B13: 45793 | C13: Japanese | D13: Giri/Haji | E13: Action | F13: 4 | G13: Good | H13: Amazon Prime | I13: 25.9 | J13: 12 | K13: =ROUND(I13*J13/100,2) -> 3.11 | L13: =ROUND(K13*0.4,2) -> 1.24
... A501: 500 | B501: 45833 | C501: Hollywood | D501: Altered Carbon S6 | E501: Crime | F501: 4 | G501: Good | H501: Hotstar | I501: 56.7 | J501: 19 | K501: =ROUND(I501*J501/100,2) -> 10.77 | L501: =ROUND(K501*0.4,2) -> 4.31

Sheet Industry Summary
A1: 📊 INDUSTRY-WISE SUMMARY
A2: Industry | B2: Total Series | C2: Avg Rating | D2: Total Viewers (M) | E2: Total Sales (₹ Cr) | F2: Total Profit (₹ Cr)
A3: Bollywood | B3: =COUNTIF('Web Series Ratings'!C2:C501,"Bollywood") -> 115 | C3: =IFERROR(ROUND(AVERAGEIF('Web Series Ratings'!C2:C501,"Bollywood",'Web Series Ratings'!F2:F501),2),"-") -> 4 | D3: =IFERROR(ROUND(SUMIF('Web Series Ratings'!C2:C501,"Bollywood",'Web Series Ratings'!I2:I501),1),"-") -> 5545.7 | E3: =IFERROR(ROUND(SUMIF('Web Series Ratings'!C2:C501,"Bollywood",'Web Series Ratings'!K2:K501),2),"-") -> 890.15 | F3: =IFERROR(ROUND(SUMIF('Web Series Ratings'!C2:C501,"Bollywood",'Web Series Ratings'!L2:L501),2),"-") -> 356.07
A4: Tollywood | B4: =COUNTIF('Web Series Ratings'!C2:C501,"Tollywood") -> 75 | C4: =IFERROR(ROUND(AVERAGEIF('Web Series Ratings'!C2:C501,"Tollywood",'Web Series Ratings'!F2:F501),2),"-") -> 4 | D4: =IFERROR(ROUND(SUMIF('Web Series Ratings'!C2:C501,"Tollywood",'Web Series Ratings'!I2:I501),1),"-") -> 3683.3 | E4: =IFERROR(ROUND(SUMIF('Web Series Ratings'!C2:C501,"Tollywood",'Web Series Ratings'!K2:K501),2),"-") -> 491.97 | F4: =IFERROR(ROUND(SUMIF('Web Series Ratings'!C2:C501,"Tollywood",'Web Series Ratings'!L2:L501),2),"-") -> 196.81
A5: Hollywood | B5: =COUNTIF('Web Series Ratings'!C2:C501,"Hollywood") -> 145 | C5: =IFERROR(ROUND(AVERAGEIF('Web Series Ratings'!C2:C501,"Hollywood",'Web Series Ratings'!F2:F501),2),"-") -> 4.08 | D5: =IFERROR(ROUND(SUMIF('Web Series Ratings'!C2:C501,"Hollywood",'Web Series Ratings'!I2:I501),1),"-") -> 8004 | E5: =IFERROR(ROUND(SUMIF('Web Series Ratings'!C2:C501,"Hollywood",'Web Series Ratings'!K2:K501),2),"-") -> 1848.62 | F5: =IFERROR(ROUND(SUMIF('Web Series Ratings'!C2:C501,"Hollywood",'Web Series Ratings'!L2:L501),2),"-") -> 739.37
A6: Chinese | B6: =COUNTIF('Web Series Ratings'!C2:C501,"Chinese") -> 80 | C6: =IFERROR(ROUND(AVERAGEIF('Web Series Ratings'!C2:C501,"Chinese",'Web Series Ratings'!F2:F501),2),"-") -> 4 | D6: =IFERROR(ROUND(SUMIF('Web Series Ratings'!C2:C501,"Chinese",'Web Series Ratings'!I2:I501),1),"-") -> 4346.3 | E6: =IFERROR(ROUND(SUMIF('Web Series Ratings'!C2:C501,"Chinese",'Web Series Ratings'!K2:K501),2),"-") -> 576.47 | F6: =IFERROR(ROUND(SUMIF('Web Series Ratings'!C2:C501,"Chinese",'Web Series Ratings'!L2:L501),2),"-") -> 230.62
A7: Japanese | B7: =COUNTIF('Web Series Ratings'!C2:C501,"Japanese") -> 85 | C7: =IFERROR(ROUND(AVERAGEIF('Web Series Ratings'!C2:C501,"Japanese",'Web Series Ratings'!F2:F501),2),"-") -> 3.92 | D7: =IFERROR(ROUND(SUMIF('Web Series Ratings'!C2:C501,"Japanese",'Web Series Ratings'!I2:I501),1),"-") -> 4138.4 | E7: =IFERROR(ROUND(SUMIF('Web Series Ratings'!C2:C501,"Japanese",'Web Series Ratings'!K2:K501),2),"-") -> 702.22 | F7: =IFERROR(ROUND(SUMIF('Web Series Ratings'!C2:C501,"Japanese",'Web Series Ratings'!L2:L501),2),"-") -> 280.91
A9: TOTAL | B9: =ROUND(SUM(B3:B7),2) -> 500 | C9: =ROUND(AVERAGE(C3:C7),2) -> 4 | D9: =ROUND(SUM(D3:D7),2) -> 25717.7 | E9: =ROUND(SUM(E3:E7),2) -> 4509.43 | F9: =ROUND(SUM(F3:F7),2) -> 1803.78

Sheet Platform Summary
A1: 📺 PLATFORM-WISE SUMMARY
A2: Platform | B2: Total Series | C2: Avg Rating | D2: Total Viewers (M) | E2: Total Sales (₹ Cr) | F2: Total Profit (₹ Cr)
A3: Netflix | B3: =COUNTIF('Web Series Ratings'!H2:H501,"Netflix") -> 94 | C3: =IFERROR(ROUND(AVERAGEIF('Web Series Ratings'!H2:H501,"Netflix",'Web Series Ratings'!F2:F501),2),"-") -> 3.99 | D3: =IFERROR(ROUND(SUMIF('Web Series Ratings'!H2:H501,"Netflix",'Web Series Ratings'!I2:I501),1),"-") -> 5040.2 | E3: =IFERROR(ROUND(SUMIF('Web Series Ratings'!H2:H501,"Netflix",'Web Series Ratings'!K2:K501),2),"-") -> 887.12 | F3: =IFERROR(ROUND(SUMIF('Web Series Ratings'!H2:H501,"Netflix",'Web Series Ratings'!L2:L501),2),"-") -> 354.8
A4: Amazon Prime | B4: =COUNTIF('Web Series Ratings'!H2:H501,"Amazon Prime") -> 102 | C4: =IFERROR(ROUND(AVERAGEIF('Web Series Ratings'!H2:H501,"Amazon Prime",'Web Series Ratings'!F2:F501),2),"-") -> 3.97 | D4: =IFERROR(ROUND(SUMIF('Web Series Ratings'!H2:H501,"Amazon Prime",'Web Series Ratings'!I2:I501),1),"-") -> 4998.5 | E4: =IFERROR(ROUND(SUMIF('Web Series Ratings'!H2:H501,"Amazon Prime",'Web Series Ratings'!K2:K501),2),"-") -> 849.47 | F4: =IFERROR(ROUND(SUMIF('Web Series Ratings'!H2:H501,"Amazon Prime",'Web Series Ratings'!L2:L501),2),"-") -> 339.74
A5: Hotstar | B5: =COUNTIF('Web Series Ratings'!H2:H501,"Hotstar") -> 104 | C5: =IFERROR(ROUND(AVERAGEIF('Web Series Ratings'!H2:H501,"Hotstar",'Web Series Ratings'!F2:F501),2),"-") -> 4.01 | D5: =IFERROR(ROUND(SUMIF('Web Series Ratings'!H2:H501,"Hotstar",'Web Series Ratings'!I2:I501),1),"-") -> 5230.3 | E5: =IFERROR(ROUND(SUMIF('Web Series Ratings'!H2:H501,"Hotstar",'Web Series Ratings'!K2:K501),2),"-") -> 909.23 | F5: =IFERROR(ROUND(SUMIF('Web Series Ratings'!H2:H501,"Hotstar",'Web Series Ratings'!L2:L501),2),"-") -> 363.75
A6: SonyLIV | B6: =COUNTIF('Web Series Ratings'!H2:H501,"SonyLIV") -> 106 | C6: =IFERROR(ROUND(AVERAGEIF('Web Series Ratings'!H2:H501,"SonyLIV",'Web Series Ratings'!F2:F501),2),"-") -> 4 | D6: =IFERROR(ROUND(SUMIF('Web Series Ratings'!H2:H501,"SonyLIV",'Web Series Ratings'!I2:I501),1),"-") -> 5294.5 | E6: =IFERROR(ROUND(SUMIF('Web Series Ratings'!H2:H501,"SonyLIV",'Web Series Ratings'!K2:K501),2),"-") -> 974.76 | F6: =IFERROR(ROUND(SUMIF('Web Series Ratings'!H2:H501,"SonyLIV",'Web Series Ratings'!L2:L501),2),"-") -> 389.92
A7: JioCinema | B7: =COUNTIF('Web Series Ratings'!H2:H501,"JioCinema") -> 94 | C7: =IFERROR(ROUND(AVERAGEIF('Web Series Ratings'!H2:H501,"JioCinema",'Web Series Ratings'!F2:F501),2),"-") -> 4.07 | D7: =IFERROR(ROUND(SUMIF('Web Series Ratings'!H2:H501,"JioCinema",'Web Series Ratings'!I2:I501),1),"-") -> 5154.2 | E7: =IFERROR(ROUND(SUMIF('Web Series Ratings'!H2:H501,"JioCinema",'Web Series Ratings'!K2:K501),2),"-") -> 888.85 | F7: =IFERROR(ROUND(SUMIF('Web Series Ratings'!H2:H501,"JioCinema",'Web Series Ratings'!L2:L501),2),"-") -> 355.57
A9: TOTAL | B9: =ROUND(SUM(B3:B7),2) -> 500 | C9: =ROUND(AVERAGE(C3:C7),2) -> 4.01 | D9: =ROUND(SUM(D3:D7),2) -> 25717.7 | E9: =ROUND(SUM(E3:E7),2) -> 4509.43 | F9: =ROUND(SUM(F3:F7),2) -> 1803.78

Sheet Genre Summary
A1: 🎭 GENRE-WISE SUMMARY
A2: Genre | B2: Total Series | C2: Avg Rating | D2: Total Viewers (M) | E2: Total Sales (₹ Cr) | F2: Total Profit (₹ Cr)
A3: Action | B3: =COUNTIF('Web Series Ratings'!E2:E501,"Action") -> 90 | C3: =IFERROR(ROUND(AVERAGEIF('Web Series Ratings'!E2:E501,"Action",'Web Series Ratings'!F2:F501),2),"-") -> 3.87 | D3: =IFERROR(ROUND(SUMIF('Web Series Ratings'!E2:E501,"Action",'Web Series Ratings'!I2:I501),1),"-") -> 4558.7 | E3: =IFERROR(ROUND(SUMIF('Web Series Ratings'!E2:E501,"Action",'Web Series Ratings'!K2:K501),2),"-") -> 785.32 | F3: =IFERROR(ROUND(SUMIF('Web Series Ratings'!E2:E501,"Action",'Web Series Ratings'!L2:L501),2),"-") -> 314.09
A4: Drama | B4: =COUNTIF('Web Series Ratings'!E2:E501,"Drama") -> 78 | C4: =IFERROR(ROUND(AVERAGEIF('Web Series Ratings'!E2:E501,"Drama",'Web Series Ratings'!F2:F501),2),"-") -> 4.09 | D4: =IFERROR(ROUND(SUMIF('Web Series Ratings'!E2:E501,"Drama",'Web Series Ratings'!I2:I501),1),"-") -> 4337.7 | E4: =IFERROR(ROUND(SUMIF('Web Series Ratings'!E2:E501,"Drama",'Web Series Ratings'!K2:K501),2),"-") -> 753.48 | F4: =IFERROR(ROUND(SUMIF('Web Series Ratings'!E2:E501,"Drama",'Web Series Ratings'!L2:L501),2),"-") -> 301.41
A5: Comedy | B5: =COUNTIF('Web Series Ratings'!E2:E501,"Comedy") -> 61 | C5: =IFERROR(ROUND(AVERAGEIF('Web Series Ratings'!E2:E501,"Comedy",'Web Series Ratings'!F2:F501),2),"-") -> 4 | D5: =IFERROR(ROUND(SUMIF('Web Series Ratings'!E2:E501,"Comedy",'Web Series Ratings'!I2:I501),1),"-") -> 2976.2 | E5: =IFERROR(ROUND(SUMIF('Web Series Ratings'!E2:E501,"Comedy",'Web Series Ratings'!K2:K501),2),"-") -> 536.16 | F5: =IFERROR(ROUND(SUMIF('Web Series Ratings'!E2:E501,"Comedy",'Web Series Ratings'!L2:L501),2),"-") -> 214.49
A6: Thriller | B6: =COUNTIF('Web Series Ratings'!E2:E501,"Thriller") -> 66 | C6: =IFERROR(ROUND(AVERAGEIF('Web Series Ratings'!E2:E501,"Thriller",'Web Series Ratings'!F2:F501),2),"-") -> 4.14 | D6: =IFERROR(ROUND(SUMIF('Web Series Ratings'!E2:E501,"Thriller",'Web Series Ratings'!I2:I501),1),"-") -> 3635.1 | E6: =IFERROR(ROUND(SUMIF('Web Series Ratings'!E2:E501,"Thriller",'Web Series Ratings'!K2:K501),2),"-") -> 637.38 | F6: =IFERROR(ROUND(SUMIF('Web Series Ratings'!E2:E501,"Thriller",'Web Series Ratings'!L2:L501),2),"-") -> 254.96
A7: Crime | B7: =COUNTIF('Web Series Ratings'!E2:E501,"Crime") -> 55 | C7: =IFERROR(ROUND(AVERAGEIF('Web Series Ratings'!E2:E501,"Crime",'Web Series Ratings'!F2:F501),2),"-") -> 4.09 | D7: =IFERROR(ROUND(SUMIF('Web Series Ratings'!E2:E501,"Crime",'Web Series Ratings'!I2:I501),1),"-") -> 2897.2 | E7: =IFERROR(ROUND(SUMIF('Web Series Ratings'!E2:E501,"Crime",'Web Series Ratings'!K2:K501),2),"-") -> 502.02 | F7: =IFERROR(ROUND(SUMIF('Web Series Ratings'!E2:E501,"Crime",'Web Series Ratings'!L2:L501),2),"-") -> 200.78
A8: Romance | B8: =COUNTIF('Web Series Ratings'!E2:E501,"Romance") -> 80 | C8: =IFERROR(ROUND(AVERAGEIF('Web Series Ratings'!E2:E501,"Romance",'Web Series Ratings'!F2:F501),2),"-") -> 3.9 | D8: =IFERROR(ROUND(SUMIF('Web Series Ratings'!E2:E501,"Romance",'Web Series Ratings'!I2:I501),1),"-") -> 3487.2 | E8: =IFERROR(ROUND(SUMIF('Web Series Ratings'!E2:E501,"Romance",'Web Series Ratings'!K2:K501),2),"-") -> 604.9 | F8: =IFERROR(ROUND(SUMIF('Web Series Ratings'!E2:E501,"Romance",'Web Series Ratings'!L2:L501),2),"-") -> 241.99
A9: Horror | B9: =COUNTIF('Web Series Ratings'!E2:E501,"Horror") -> 35 | C9: =IFERROR(ROUND(AVERAGEIF('Web Series Ratings'!E2:E501,"Horror",'Web Series Ratings'!F2:F501),2),"-") -> 3.97 | D9: =IFERROR(ROUND(SUMIF('Web Series Ratings'!E2:E501,"Horror",'Web Series Ratings'!I2:I501),1),"-") -> 1641.8 | E9: =IFERROR(ROUND(SUMIF('Web Series Ratings'!E2:E501,"Horror",'Web Series Ratings'!K2:K501),2),"-") -> 306.83 | F9: =IFERROR(ROUND(SUMIF('Web Series Ratings'!E2:E501,"Horror",'Web Series Ratings'!L2:L501),2),"-") -> 122.73
A10: Fantasy | B10: =COUNTIF('Web Series Ratings'!E2:E501,"Fantasy") -> 35 | C10: =IFERROR(ROUND(AVERAGEIF('Web Series Ratings'!E2:E501,"Fantasy",'Web Series Ratings'!F2:F501),2),"-") -> 4.11 | D10: =IFERROR(ROUND(SUMIF('Web Series Ratings'!E2:E501,"Fantasy",'Web Series Ratings'!I2:I501),1),"-") -> 2183.8 | E10: =IFERROR(ROUND(SUMIF('Web Series Ratings'!E2:E501,"Fantasy",'Web Series Ratings'!K2:K501),2),"-") -> 383.34 | F10: =IFERROR(ROUND(SUMIF('Web Series Ratings'!E2:E501,"Fantasy",'Web Series Ratings'!L2:L501),2),"-") -> 153.33
A12: TOTAL | B12: =ROUND(SUM(B3:B10),2) -> 500 | C12: =ROUND(AVERAGE(C3:C10),2) -> 4.02 | D12: =ROUND(SUM(D3:D10),2) -> 25717.7 | E12: =ROUND(SUM(E3:E10),2) -> 4509.43 | F12: =ROUND(SUM(F3:F10),2) -> 1803.78

Sheet final_dashboard
A1: WEB SERIES RATING AND REVENUE DASHBOARD

Sheet dash board
A3: Row Labels | B3: Total Sales((₹ Crore) | D3: Row Labels | E3: Count of Viewers | G3: Row Labels | H3: profit(₹ Crore) | J3: Row Labels | K3: Sum of Total Sales (₹ Crore) | M3: Row Labels | N3: Sum of Total Sales (₹ Crore) | P3: Row Labels | Q3: Sum of Total Sales (₹ Crore)
A4: Bollywood | B4: 890.15 | D4: Action | E4: 90 | G4: Amazon Prime | H4: 339.74 | J4: 24 S4 | K4: 40.18 | M4: Bard of Blood S5 | N4: 0.27 | P4: Jan | Q4: 609.62
A5: Chinese | B5: 576.47 | D5: Comedy | E5: 61 | G5: Hotstar | H5: 363.75 | J5: Big Bang Theory S3 | K5: 35.91 | M5: Erased S6 | N5: 0.23 | P5: Feb | Q5: 887.47
A6: Hollywood | B6: 1848.62 | D6: Crime | E6: 55 | G6: JioCinema | H6: 355.57 | J6: How I Met Your Mother | K6: 36.88 | M6: Hometown Cha-Cha-Cha S4 | N6: 0.38 | P6: Mar | Q6: 683.62
A7: Japanese | B7: 702.22 | D7: Drama | E7: 78 | G7: Netflix | H7: 354.8 | J7: Money Heist | K7: 36.48 | M7: Nirvana in Fire S2 | N7: 0.32 | P7: Apr | Q7: 828.2
A8: Tollywood | B8: 491.97 | D8: Fantasy | E8: 35 | G8: SonyLIV | H8: 389.92 | J8: Reign S3 | K8: 38.98 | M8: Thaen S7 | N8: 0.22 | P8: May | Q8: 780.61
D9: Horror | E9: 35 | J9: Stranger Things | K9: 37.36 | M9: Tooth Pari S7 | N9: 0.17 | P9: Jun | Q9: 719.91
D10: Romance | E10: 80
D11: Thriller | E11: 66
